CHANGELOG.txt
LICENSE.txt
MANIFEST.in
README.txt
setup.py
pypattern/__init__.py
pypattern.egg-info/PKG-INFO
pypattern.egg-info/SOURCES.txt
pypattern.egg-info/dependency_links.txt
pypattern.egg-info/top_level.txt
pypattern/capital_letters/__init__.py
pypattern/numbers/__init__.py
pypattern/small_letters/__init__.py
pypattern/special_characters/__init__.py