Metadata-Version: 2.1
Name: pypattern
Version: 0.0.3
Summary: Simple Python module for printing patterns for characters (Lower case and Upper case), numbers and special characters.
Home-page: https://github.com/fazil2003/pypattern
Author: Mohamed Fazil
Author-email: mohamedfazil463@gmail.com
License: MIT
Keywords: fazil,pypattern,pattern,patterns,printing,stars
Platform: UNKNOWN
Classifier: Development Status :: 5 - Production/Stable
Classifier: Intended Audience :: Education
Classifier: Operating System :: Microsoft :: Windows :: Windows 10
Classifier: License :: OSI Approved :: MIT License
Classifier: Programming Language :: Python :: 3
License-File: LICENSE.txt
